cache_memoize/__init__.py
django_cache_memoize-0.2.0.dist-info/AUTHORS.rst
django_cache_memoize-0.2.0.dist-info/LICENSE
django_cache_memoize-0.2.0.dist-info/METADATA
django_cache_memoize-0.2.0.dist-info/WHEEL
django_cache_memoize-0.2.0.dist-info/top_level.txt
django_cache_memoize-0.2.0.dist-info/RECORD
