Metadata-Version: 2.1
Name: django-cache-memoize
Version: 0.2.0
Summary: Django utility for a memoization decorator that uses the Django cache framework.
Home-page: https://github.com/peterbe/django-cache-memoize
Author: Peter Bengtsson
Author-email: mail@peterbe.com
License: MPL-2.0
Keywords: django,memoize,cache,decorator
Platform: UNKNOWN
Classifier: Development Status :: 5 - Production/Stable
Classifier: Environment :: Web Environment :: Mozilla
Classifier: Framework :: Django
Classifier: Intended Audience :: Developers
Classifier: License :: OSI Approved :: Mozilla Public License 2.0 (MPL 2.0)
Classifier: License :: OSI Approved :: MIT License
Classifier: Programming Language :: Python :: 3
Classifier: Programming Language :: Python :: 3.8
Classifier: Programming Language :: Python :: 3.9
Classifier: Programming Language :: Python :: 3.10
Classifier: Programming Language :: Python :: 3.11
Classifier: Programming Language :: Python :: 3 :: Only
Classifier: Topic :: Internet :: WWW/HTTP
Requires-Python: >=3.8
Provides-Extra: dev
Requires-Dist: flake8 ; extra == 'dev'
Requires-Dist: tox ; extra == 'dev'
Requires-Dist: twine ; extra == 'dev'
Requires-Dist: therapist ; extra == 'dev'
Requires-Dist: black ; extra == 'dev'
